<?xml version="1.0" encoding="UTF-8"?>
<!DOCTYPE mapper PUBLIC "-//mybatis.org//DTD Mapper 3.0//EN" "http://mybatis.org/dtd/mybatis-3-mapper.dtd">
<mapper namespace="com.example.dao.PetKnowledgeMapper">
  <resultMap id="BaseResultMap" type="com.example.pojo.PetKnowledge">
    <!--
      WARNING - @mbg.generated
      This element is automatically generated by MyBatis Generator, do not modify.
    -->
    <id column="kno_id" jdbcType="INTEGER" property="knoId" />
    <result column="kno_title" jdbcType="VARCHAR" property="knoTitle" />
    <result column="kno_category" jdbcType="VARCHAR" property="knoCategory" />
    <result column="specie_id" jdbcType="INTEGER" property="specieId" />
    <result column="variety_id" jdbcType="INTEGER" property="varietyId" />
    <result column="kno_images" jdbcType="VARCHAR" property="knoImages" />
    <result column="created_at" jdbcType="TIMESTAMP" property="createdAt" />
    <result column="updated_at" jdbcType="TIMESTAMP" property="updatedAt" />
    <result column="kno_content" jdbcType="LONGVARCHAR" property="knoContent" />
  </resultMap>
  <delete id="deleteByPrimaryKey" parameterType="java.lang.Integer">
    <!--
      WARNING - @mbg.generated
      This element is automatically generated by MyBatis Generator, do not modify.
    -->
    delete from pet_knowledge
    where kno_id = #{knoId,jdbcType=INTEGER}
  </delete>
  <insert id="insert" parameterType="com.example.pojo.PetKnowledge">
    <!--
      WARNING - @mbg.generated
      This element is automatically generated by MyBatis Generator, do not modify.
    -->
    insert into pet_knowledge (kno_id, kno_title, kno_category, 
      specie_id, variety_id, kno_images, 
      created_at, updated_at, kno_content
      )
    values (#{knoId,jdbcType=INTEGER}, #{knoTitle,jdbcType=VARCHAR}, #{knoCategory,jdbcType=VARCHAR}, 
      #{specieId,jdbcType=INTEGER}, #{varietyId,jdbcType=INTEGER}, #{knoImages,jdbcType=VARCHAR}, 
      #{createdAt,jdbcType=TIMESTAMP}, #{updatedAt,jdbcType=TIMESTAMP}, #{knoContent,jdbcType=LONGVARCHAR}
      )
  </insert>
  <update id="updateByPrimaryKey" parameterType="com.example.pojo.PetKnowledge">
    <!--
      WARNING - @mbg.generated
      This element is automatically generated by MyBatis Generator, do not modify.
    -->
    update pet_knowledge
    set kno_title = #{knoTitle,jdbcType=VARCHAR},
      kno_category = #{knoCategory,jdbcType=VARCHAR},
      specie_id = #{specieId,jdbcType=INTEGER},
      variety_id = #{varietyId,jdbcType=INTEGER},
      kno_images = #{knoImages,jdbcType=VARCHAR},
      created_at = #{createdAt,jdbcType=TIMESTAMP},
      updated_at = #{updatedAt,jdbcType=TIMESTAMP},
      kno_content = #{knoContent,jdbcType=LONGVARCHAR}
    where kno_id = #{knoId,jdbcType=INTEGER}
  </update>
  <select id="selectByPrimaryKey" parameterType="java.lang.Integer" resultMap="BaseResultMap">
    <!--
      WARNING - @mbg.generated
      This element is automatically generated by MyBatis Generator, do not modify.
    -->
    select kno_id, kno_title, kno_category, specie_id, variety_id, kno_images, created_at, 
    updated_at, kno_content
    from pet_knowledge
    where kno_id = #{knoId,jdbcType=INTEGER}
  </select>
  <select id="selectAll" resultMap="BaseResultMap">
    <!--
      WARNING - @mbg.generated
      This element is automatically generated by MyBatis Generator, do not modify.
    -->
    select kno_id, kno_title, kno_category, specie_id, variety_id, kno_images, created_at, 
    updated_at, kno_content
    from pet_knowledge
  </select>
</mapper>